Metadata-Version: 2.1
Name: andeplane_reveal_streamlit_component
Version: 0.1.5
Summary: Streamlit wrapper for Cognite Reveal to view 3D content from Cognite Data Fsion
Home-page: 
Author: John Smith
Author-email: john@example.com
Requires-Python: >=3.7
Requires-Dist: streamlit >=0.63
Provides-Extra: devel
Requires-Dist: wheel ; extra == 'devel'
Requires-Dist: pytest ==7.4.0 ; extra == 'devel'
Requires-Dist: playwright ==1.39.0 ; extra == 'devel'
Requires-Dist: requests ==2.31.0 ; extra == 'devel'
Requires-Dist: pytest-playwright-snapshot ==1.0 ; extra == 'devel'
Requires-Dist: pytest-rerunfailures ==12.0 ; extra == 'devel'
